llama_stack_api/__init__.py
llama_stack_api/agents.py
llama_stack_api/connectors.py
llama_stack_api/conversations.py
llama_stack_api/datasetio.py
llama_stack_api/datatypes.py
llama_stack_api/eval.py
llama_stack_api/inference.py
llama_stack_api/models.py
llama_stack_api/openai_responses.py
llama_stack_api/post_training.py
llama_stack_api/prompts.py
llama_stack_api/rag_tool.py
llama_stack_api/resource.py
llama_stack_api/router_utils.py
llama_stack_api/safety.py
llama_stack_api/schema_utils.py
llama_stack_api/scoring.py
llama_stack_api/scoring_functions.py
llama_stack_api/shields.py
llama_stack_api/tools.py
llama_stack_api/vector_io.py
llama_stack_api/vector_stores.py
llama_stack_api/version.py
llama_stack_api/admin/__init__.py
llama_stack_api/admin/api.py
llama_stack_api/admin/fastapi_routes.py
llama_stack_api/admin/models.py
llama_stack_api/batches/__init__.py
llama_stack_api/batches/api.py
llama_stack_api/batches/fastapi_routes.py
llama_stack_api/batches/models.py
llama_stack_api/benchmarks/__init__.py
llama_stack_api/benchmarks/api.py
llama_stack_api/benchmarks/fastapi_routes.py
llama_stack_api/benchmarks/models.py
llama_stack_api/common/__init__.py
llama_stack_api/common/content_types.py
llama_stack_api/common/errors.py
llama_stack_api/common/job_types.py
llama_stack_api/common/responses.py
llama_stack_api/common/training_types.py
llama_stack_api/common/type_system.py
llama_stack_api/datasets/__init__.py
llama_stack_api/datasets/api.py
llama_stack_api/datasets/fastapi_routes.py
llama_stack_api/datasets/models.py
llama_stack_api/file_processors/__init__.py
llama_stack_api/file_processors/api.py
llama_stack_api/file_processors/fastapi_routes.py
llama_stack_api/file_processors/models.py
llama_stack_api/files/__init__.py
llama_stack_api/files/api.py
llama_stack_api/files/fastapi_routes.py
llama_stack_api/files/models.py
llama_stack_api/inspect_api/__init__.py
llama_stack_api/inspect_api/api.py
llama_stack_api/inspect_api/fastapi_routes.py
llama_stack_api-0.4.4.dist-info/METADATA
llama_stack_api-0.4.4.dist-info/WHEEL
llama_stack_api-0.4.4.dist-info/top_level.txt
llama_stack_api-0.4.4.dist-info/RECORD
