Metadata-Version: 2.4
Name: llama-stack-api
Version: 0.4.4
Summary: API and Provider specifications for Llama Stack - lightweight package with protocol definitions and provider specs
Author-email: Meta Llama <llama-oss@meta.com>
License: MIT
Project-URL: Homepage, https://github.com/llamastack/llama-stack
Classifier: License :: OSI Approved :: MIT License
Classifier: Programming Language :: Python :: 3
Classifier: Operating System :: OS Independent
Classifier: Intended Audience :: Developers
Classifier: Intended Audience :: Information Technology
Classifier: Intended Audience :: Science/Research
Classifier: Topic :: Scientific/Engineering :: Artificial Intelligence
Classifier: Topic :: Scientific/Engineering :: Information Analysis
Requires-Python: >=3.12
Requires-Dist: openai>=2.5.0
Requires-Dist: fastapi<1.0,>=0.115.0
Requires-Dist: pydantic>=2.11.9
Requires-Dist: jsonschema
Requires-Dist: opentelemetry-sdk>=1.30.0
Requires-Dist: opentelemetry-exporter-otlp-proto-http>=1.30.0
